{
    "info": {
        "name": "Three-Way Match API",
        "description": "API collection for testing the Three-Way Match Engine",
        "schema": "https://schema.getpostman.com/json/collection/v2.1.0/collection.json"
    },
    "item": [
        {
            "name": "Health Check",
            "request": {
                "method": "GET",
                "header": [],
                "url": {
                    "raw": "http://localhost:3000/health",
                    "protocol": "http",
                    "host": [
                        "localhost"
                    ],
                    "port": "3000",
                    "path": [
                        "health"
                    ]
                }
            },
            "response": []
        },
        {
            "name": "Upload PO Document",
            "request": {
                "method": "POST",
                "header": [],
                "body": {
                    "mode": "formdata",
                    "formdata": [
                        {
                            "key": "file",
                            "type": "file",
                            "src": []
                        },
                        {
                            "key": "documentType",
                            "value": "po",
                            "type": "text"
                        }
                    ]
                },
                "url": {
                    "raw": "http://localhost:3000/documents/upload",
                    "protocol": "http",
                    "host": [
                        "localhost"
                    ],
                    "port": "3000",
                    "path": [
                        "documents",
                        "upload"
                    ]
                }
            },
            "response": []
        },
        {
            "name": "Upload GRN Document",
            "request": {
                "method": "POST",
                "header": [],
                "body": {
                    "mode": "formdata",
                    "formdata": [
                        {
                            "key": "file",
                            "type": "file",
                            "src": []
                        },
                        {
                            "key": "documentType",
                            "value": "grn",
                            "type": "text"
                        }
                    ]
                },
                "url": {
                    "raw": "http://localhost:3000/documents/upload",
                    "protocol": "http",
                    "host": [
                        "localhost"
                    ],
                    "port": "3000",
                    "path": [
                        "documents",
                        "upload"
                    ]
                }
            },
            "response": []
        },
        {
            "name": "Upload Invoice Document",
            "request": {
                "method": "POST",
                "header": [],
                "body": {
                    "mode": "formdata",
                    "formdata": [
                        {
                            "key": "file",
                            "type": "file",
                            "src": []
                        },
                        {
                            "key": "documentType",
                            "value": "invoice",
                            "type": "text"
                        }
                    ]
                },
                "url": {
                    "raw": "http://localhost:3000/documents/upload",
                    "protocol": "http",
                    "host": [
                        "localhost"
                    ],
                    "port": "3000",
                    "path": [
                        "documents",
                        "upload"
                    ]
                }
            },
            "response": []
        },
        {
            "name": "Get Document by ID",
            "request": {
                "method": "GET",
                "header": [],
                "url": {
                    "raw": "http://localhost:3000/documents/:id",
                    "protocol": "http",
                    "host": [
                        "localhost"
                    ],
                    "port": "3000",
                    "path": [
                        "documents",
                        ":id"
                    ],
                    "variable": [
                        {
                            "key": "id",
                            "value": "YOUR_DOCUMENT_ID_HERE"
                        }
                    ]
                }
            },
            "response": []
        },
        {
            "name": "Get Match Result",
            "request": {
                "method": "GET",
                "header": [],
                "url": {
                    "raw": "http://localhost:3000/match/:poNumber",
                    "protocol": "http",
                    "host": [
                        "localhost"
                    ],
                    "port": "3000",
                    "path": [
                        "match",
                        ":poNumber"
                    ],
                    "variable": [
                        {
                            "key": "poNumber",
                            "value": "CI4PO05788"
                        }
                    ]
                }
            },
            "response": []
        }
    ]
}
